CHANGES.rst
CONTRIBUTORS.rst
DEVELOP.rst
LICENSE.GPL
LICENSE.rst
MANIFEST.in
README.md
setup.cfg
setup.py
docs/README.txt
docs/Typesense.drawio
docs/Typesense.png
docs/Typesense.svg
docs/conf.py
docs/index.rst
docs/typesense-administration.png
docs/typesense-features.png
docs/typesense-search.png
docs/typesense-settings.png
src/zopyx/__init__.py
src/zopyx.typesense.egg-info/PKG-INFO
src/zopyx.typesense.egg-info/SOURCES.txt
src/zopyx.typesense.egg-info/dependency_links.txt
src/zopyx.typesense.egg-info/entry_points.txt
src/zopyx.typesense.egg-info/namespace_packages.txt
src/zopyx.typesense.egg-info/not-zip-safe
src/zopyx.typesense.egg-info/requires.txt
src/zopyx.typesense.egg-info/top_level.txt
src/zopyx/typesense/README.txt
src/zopyx/typesense/__init__.py
src/zopyx/typesense/api.py
src/zopyx/typesense/cmd.py
src/zopyx/typesense/config.py
src/zopyx/typesense/configure.zcml
src/zopyx/typesense/huey_tasks.py
src/zopyx/typesense/indexer.py
src/zopyx/typesense/interfaces.py
src/zopyx/typesense/permissions.zcml
src/zopyx/typesense/setuphandlers.py
src/zopyx/typesense/testing.py
src/zopyx/typesense/adapters/__init__.py
src/zopyx/typesense/adapters/configure.zcml
src/zopyx/typesense/adapters/document.py
src/zopyx/typesense/adapters/file.py
src/zopyx/typesense/browser/__init__.py
src/zopyx/typesense/browser/admin.pt
src/zopyx/typesense/browser/configure.zcml
src/zopyx/typesense/browser/controlpanel.py
src/zopyx/typesense/browser/de-news.json
src/zopyx/typesense/browser/indexed_content.pt
src/zopyx/typesense/browser/search.html
src/zopyx/typesense/browser/search.pt
src/zopyx/typesense/browser/views.py
src/zopyx/typesense/browser/overrides/.gitkeep
src/zopyx/typesense/browser/static/.gitkeep
src/zopyx/typesense/browser/static/algoliasearchLite.min.js
src/zopyx/typesense/browser/static/app.js
src/zopyx/typesense/browser/static/instantsearch.js
src/zopyx/typesense/browser/static/search.css
src/zopyx/typesense/browser/static/typesense-instantsearch-adapter.min.js
src/zopyx/typesense/browser/static/typesense.min.js
src/zopyx/typesense/locales/README.rst
src/zopyx/typesense/locales/__init__.py
src/zopyx/typesense/locales/update.py
src/zopyx/typesense/locales/update.sh
src/zopyx/typesense/locales/zopyx.typesense.pot
src/zopyx/typesense/locales/en/LC_MESSAGES/zopyx.typesense.mo
