Metadata-Version: 2.1
Name: zopyx.typesense
Version: 1.0.0a8
Summary: Typesense integration with Plone 6
Home-page: https://github.com/zopyx/zopyx.typesense
Author: Andreas Jung
Author-email: info@zopyx.com
License: GPL version 2
Project-URL: PyPI, https://pypi.python.org/pypi/zopyx.typesense
Project-URL: Source, https://github.com/zopyx/zopyx.typesense
Project-URL: Tracker, https://github.com/zopyx/zopyx.typesense/issues
Keywords: Python Plone CMS search fulltext indexing factedsearch Typesense
Platform: UNKNOWN
Classifier: Environment :: Web Environment
Classifier: Framework :: Plone
Classifier: Framework :: Plone :: Addon
Classifier: Framework :: Plone :: 5.2
Classifier: Framework :: Plone :: 6.0
Classifier: Programming Language :: Python
Classifier: Programming Language :: Python :: 3.8
Classifier: Programming Language :: Python :: 3.9
Classifier: Operating System :: OS Independent
Classifier: License :: OSI Approved :: GNU General Public License v2 (GPLv2)
Provides-Extra: test
License-File: LICENSE.GPL
License-File: LICENSE.rst
